fseq2/__init__.py
fseq2/callpeak_idr_main.py
fseq2/callpeak_main.py
fseq2/fseq2.py
fseq2/idr_main.py
fseq2/idr_2_0_3/__init__.py
fseq2/idr_2_0_3/examine_inv_cdf.py
fseq2/idr_2_0_3/idr.py
fseq2/idr_2_0_3/inv_cdf.c
fseq2/idr_2_0_3/inv_cdf.cpython-312-darwin.so
fseq2/idr_2_0_3/optimization.py
fseq2/idr_2_0_3/stuff_i_pbly_wont_use.py
fseq2/idr_2_0_3/symbolic.py
fseq2/idr_2_0_3/utility.py
fseq2-2.0.4.data/scripts/fseq2
fseq2-2.0.4.dist-info/AUTHORS.rst
fseq2-2.0.4.dist-info/LICENSE
fseq2-2.0.4.dist-info/METADATA
fseq2-2.0.4.dist-info/WHEEL
fseq2-2.0.4.dist-info/top_level.txt
fseq2-2.0.4.dist-info/RECORD
