Metadata-Version: 2.1
Name: fseq2
Version: 2.0.4
Summary: Improving the feature density based peak caller with dynamic statistics.
Home-page: https://github.com/Boyle-Lab/F-Seq2
Author: Nanxiang Zhao (Samuel)
Author-email: samzhao@umich.edu
License: GNU General Public License v3
Keywords: fseq2
Classifier: Development Status :: 3 - Alpha
Classifier: Intended Audience :: Developers
Classifier: License :: OSI Approved :: GNU General Public License v3 (GPLv3)
Classifier: Natural Language :: English
Classifier: Programming Language :: Python :: 3.9
Classifier: Programming Language :: Python :: 3.10
Classifier: Programming Language :: Python :: 3.11
Classifier: Programming Language :: Python :: 3.12
Requires-Python: >=3.9
License-File: LICENSE
License-File: AUTHORS.rst
Requires-Dist: numpy<2.0
Requires-Dist: scipy>=1.1.0
Requires-Dist: pandas>=0.24
Requires-Dist: statsmodels
Requires-Dist: KDEpy
Requires-Dist: pybedtools
Requires-Dist: pyBigWig
Requires-Dist: h5py
Requires-Dist: matplotlib
Requires-Dist: cython
